scaling_law_probe/__init__.py
scaling_law_probe/__main__.py
scaling_law_probe/probe.py
scaling_law_probe/encoders/__init__.py
scaling_law_probe/encoders/text.py
scaling_law_probe/probes/__init__.py
scaling_law_probe/probes/twonn.py
scaling_law_probe-0.1.0.dist-info/licenses/LICENSE
scaling_law_probe-0.1.0.dist-info/METADATA
scaling_law_probe-0.1.0.dist-info/WHEEL
scaling_law_probe-0.1.0.dist-info/entry_points.txt
scaling_law_probe-0.1.0.dist-info/top_level.txt
scaling_law_probe-0.1.0.dist-info/RECORD
