Metadata-Version: 2.4
Name: scaling-law-probe
Version: 0.1.0
Summary: Predict neural scaling laws from data geometry before expensive training runs
Author: Sandro Andric
License-Expression: MIT
Project-URL: Homepage, https://github.com/sandroandric/neural-scaling-probe
Project-URL: Documentation, https://github.com/sandroandric/neural-scaling-probe#readme
Project-URL: Repository, https://github.com/sandroandric/neural-scaling-probe
Project-URL: Issues, https://github.com/sandroandric/neural-scaling-probe/issues
Keywords: machine-learning,scaling-laws,intrinsic-dimension,neural-networks,deep-learning
Classifier: Development Status :: 4 - Beta
Classifier: Intended Audience :: Science/Research
Classifier: Programming Language :: Python :: 3
Classifier: Programming Language :: Python :: 3.8
Classifier: Programming Language :: Python :: 3.9
Classifier: Programming Language :: Python :: 3.10
Classifier: Programming Language :: Python :: 3.11
Classifier: Topic :: Scientific/Engineering :: Artificial Intelligence
Requires-Python: >=3.8
License-File: LICENSE
Requires-Dist: numpy>=1.20
Requires-Dist: scipy>=1.7
Requires-Dist: transformers>=4.20
Requires-Dist: torch>=1.10
Provides-Extra: dev
Requires-Dist: pytest>=7.0; extra == "dev"
Requires-Dist: pytest-cov; extra == "dev"
Requires-Dist: black; extra == "dev"
Requires-Dist: isort; extra == "dev"
Requires-Dist: mypy; extra == "dev"
Provides-Extra: datasets
Requires-Dist: datasets>=2.0; extra == "datasets"
Provides-Extra: all
Requires-Dist: scaling-law-probe[datasets,dev]; extra == "all"
Dynamic: license-file
